duolingo.py
duolingo_api-0.5.4.dist-info/LICENSE.md
duolingo_api-0.5.4.dist-info/METADATA
duolingo_api-0.5.4.dist-info/WHEEL
duolingo_api-0.5.4.dist-info/top_level.txt
duolingo_api-0.5.4.dist-info/RECORD
