Metadata-Version: 2.1
Name: duolingo-api
Version: 0.5.4
Summary: Unofficial API for duolingo.com
Home-page: https://github.com/KartikTalwar/duolingo
Author: Kartik Talwar
Author-email: hi@kartikt.com
License: MIT
Keywords: duolingo,duolingo api,language
Platform: UNKNOWN
Classifier: Development Status :: 3 - Alpha
Classifier: Intended Audience :: Developers
Classifier: License :: OSI Approved :: MIT License
Classifier: Operating System :: OS Independent
Classifier: Programming Language :: Python
Classifier: Programming Language :: Python :: 3.4
Classifier: Programming Language :: Python :: 3.5
Classifier: Programming Language :: Python :: 3.6
Classifier: Programming Language :: Python :: 3.7
Classifier: Programming Language :: Python :: 3.8
Classifier: Topic :: Software Development
Classifier: Topic :: Software Development :: Libraries
Classifier: Topic :: Software Development :: Libraries :: Python Modules
Requires-Dist: requests
